Workbook

Sheet Panel
B2: PLAN DE CIERRE DE TARJETAS — PANEL DE CONTROL
B4: Ingreso mensual total | C4: =Movimientos!D4
B5: Gastos fijos | C5: =Movimientos!D5
B6: Presupuesto disponible para tarjetas | C6: =C4-C5
B7: Saldo total tarjetas (hoy) | C7: =Deudas!D9
B9: Estado | C9: =IF(C7<=0,"✅ TARJETAS PAGADAS","⏳ En proceso")
B11: Resumen y cuadre por mes
B12: Mes | C12: Ingreso Total | D12: Gasto Total | E12: Diferencia | F12: ¿Cuadra? | G12: Pago Tarjetas | H12: Saldo Restante Tarjetas | I12: ¿Cerradas?
B13: Mes 1 | C13: ='Mes 1'!C6 | D13: ='Mes 1'!C48 | E13: ='Mes 1'!C49 | F13: ='Mes 1'!C50 | G13: =SUMIFS('Mes 1'!$F:$F,'Mes 1'!$G:$G,"Deuda") | H13: =MAX(3477125-(G13),0) | I13: =IF(H13<=0,"✅ Sí","⏳ No")
B14: Mes 2 | C14: ='Mes 2'!C6 | D14: ='Mes 2'!C48 | E14: ='Mes 2'!C49 | F14: ='Mes 2'!C50 | G14: =SUMIFS('Mes 2'!$F:$F,'Mes 2'!$G:$G,"Deuda") | H14: =MAX(3477125-(G13+G14),0) | I14: =IF(H14<=0,"✅ Sí","⏳ No")
B15: Mes 3 | C15: ='Mes 3'!C6 | D15: ='Mes 3'!C48 | E15: ='Mes 3'!C49 | F15: ='Mes 3'!C50 | G15: =SUMIFS('Mes 3'!$F:$F,'Mes 3'!$G:$G,"Deuda") | H15: =MAX(3477125-(G13+G14+G15),0) | I15: =IF(H15<=0,"✅ Sí","⏳ No")
B18: Instrucciones rápidas
B19: 1) Registra cada movimiento real en la pestaña del mes correspondiente ('Mes 1', 'Mes 2', 'Mes 3'), indicando la quincena. 2) Cada hoja de mes te dice sola si 'Cuadra' (ingreso quincenal vs. lo gastado) al final. 3) Las pestañas 'Deudas' y este Panel se actualizan solas sumando las 3 hojas de mes. 4) Cuando 'Saldo total tarjetas' llegue a 0, vuelve al chat para el nuevo plan (Confama + ahorro).

Sheet Deudas
B2: MATRIZ DE DEUDAS — TARJETAS
B4: Acreedor | C4: Saldo Inicial | D4: Tasa EA (%) | E4: Cuota Mínima | F4: Total Abonado (auto) | G4: Saldo Actual (auto) | H4: Estado
B5: Bancolombia 1 | C5: 455640 | D5: 0.296152 | E5: 164806 | F5: =SUMIFS('Mes 1'!$F:$F,'Mes 1'!$E:$E,B5)+SUMIFS('Mes 2'!$F:$F,'Mes 2'!$E:$E,B5)+SUMIFS('Mes 3'!$F:$F,'Mes 3'!$E:$E,B5) | G5: =MAX(C5-F5,0) | H5: =IF(G5<=0,"✅ Pagada","⏳ Pendiente")
B6: Bancolombia 2 | C6: 3128 | D6: 0.296152 | E6: 3128 | F6: =SUMIFS('Mes 1'!$F:$F,'Mes 1'!$E:$E,B6)+SUMIFS('Mes 2'!$F:$F,'Mes 2'!$E:$E,B6)+SUMIFS('Mes 3'!$F:$F,'Mes 3'!$E:$E,B6) | G6: =MAX(C6-F6,0) | H6: =IF(G6<=0,"✅ Pagada","⏳ Pendiente")
B7: Tarjeta Nu | C7: 3018357 | D7: 0.292 | E7: 1100000 | F7: =SUMIFS('Mes 1'!$F:$F,'Mes 1'!$E:$E,B7)+SUMIFS('Mes 2'!$F:$F,'Mes 2'!$E:$E,B7)+SUMIFS('Mes 3'!$F:$F,'Mes 3'!$E:$E,B7) | G7: =MAX(C7-F7,0) | H7: =IF(G7<=0,"✅ Pagada","⏳ Pendiente")
B9: TOTAL | C9: =SUM(C5:C7) | D9: =SUM(D5:D7) | F9: =SUM(F5:F7) | G9: =SUM(G5:G7)
B11: Nota: 'Total Abonado' se calcula solo con lo que registres en la pestaña Movimientos usando el desplegable de 'Acreedor' (debe coincidir exacto con el nombre de esta tabla).

Sheet Gastos Fijos
B2: GASTOS FIJOS MENSUALES
B4: Rubro | C4: Valor Mensual | D4: Guardar Quincena 1 | E4: Guardar Quincena 2
B5: Vivienda (Arriendo) | C5: 1600000 | D5: =ROUND(C5/2,0) | E5: =C5-D5
B6: Servicios (Agua, luz, gas, internet) | C6: 339600 | D6: =ROUND(C6/2,0) | E6: =C6-D6
B7: Préstamo Confama | C7: 775054 | D7: =ROUND(C7/2,0) | E7: =C7-D7
B8: Transporte/Gasolina | C8: 50000 | D8: =ROUND(C8/2,0) | E8: =C8-D8
B9: Seguros y Suscripciones | C9: 259200 | D9: =ROUND(C9/2,0) | E9: =C9-D9
B10: Otros fijos | C10: 100000 | D10: =ROUND(C10/2,0) | E10: =C10-D10
B11: Imprevistos | C11: 100000 | D11: =ROUND(C11/2,0) | E11: =C11-D11
B12: TOTAL GASTOS FIJOS | C12: =SUM(C5:C11) | D12: =SUM(D5:D11) | E12: =SUM(E5:E11)
B14: Nota: 'Quincena 1' = primeros 15 días del mes, 'Quincena 2' = resto del mes. Divide cada rubro a la mitad para separar cuánto apartar en cada pago de nómina quincenal.
B17: INGRESOS
B18: Ingreso Fijo Neto | C18: 4500000
B19: Ingreso Variable/Extra (promedio) | C19: 600000
B20: TOTAL INGRESOS | C20: =SUM(C18:C19)
B21: TOTAL GASTOS FIJOS | C21: =C12
B24: CUOTAS DE TARJETAS (mientras estén activas)
B25: Acreedor | C25: Cuota Mensual | D25: Guardar Quincena 1 | E25: Guardar Quincena 2
B26: Bancolombia 1 | C26: 164806 | D26: =ROUND(C26/2,0) | E26: =C26-D26
B27: Bancolombia 2 | C27: 3128 | D27: =ROUND(C27/2,0) | E27: =C27-D27
B28: Tarjeta Nu | C28: 1100000 | D28: =ROUND(C28/2,0) | E28: =C28-D28
B29: TOTAL CUOTAS TARJETAS | C29: =SUM(C26:C28) | D29: =SUM(D26:D28) | E29: =SUM(E26:E28)
B31: Nota: estas cuotas son las MÍNIMAS. Mientras el plan de avalancha esté activo, se paga más que esto (ver pestaña Deudas/Panel); esta tabla es solo el piso mínimo a apartar por quincena.

Sheet Mes 1
B2: MOVIMIENTOS — MES 1
B4: Ingreso Quincena 1 | C4: =ROUND('Gastos Fijos'!C20/2,0)
B5: Ingreso Quincena 2 | C5: ='Gastos Fijos'!C20-C4
B6: INGRESO TOTAL MES | C6: =C4+C5
B8: Fecha | C8: Quincena | D8: Categoría | E8: Acreedor (si es pago tarjeta) | F8: Valor | G8: Tipo | H8: Notas
B9: Ej: 2026-08-20 | C9: Quincena 1 | D9: Pago tarjeta | E9: Bancolombia 2 | F9: 3128 | G9: Deuda | H9: Saldar completa
B10: Ej: 2026-08-20 | C10: Quincena 1 | D10: Pago tarjeta | E10: Bancolombia 1 | F10: 455640 | G10: Deuda | H10: Pago total
B11: Ej: 2026-08-20 | C11: Quincena 1 | D11: Pago tarjeta | E11: Tarjeta Nu | F11: 1417378 | G11: Deuda | H11: Abono con excedente
B43: RESUMEN Y CUADRE
B44: Gastado Quincena 1 | C44: =SUMIFS(F9:F40,C9:C40,"Quincena 1")
B45: Gastado Quincena 2 | C45: =SUMIFS(F9:F40,C9:C40,"Quincena 2")
B46: Saldo Quincena 1 (Ingreso - Gastado) | C46: =C4-C44
B47: Saldo Quincena 2 (Ingreso - Gastado) | C47: =C5-C45
B48: Gasto Total del Mes | C48: =C44+C45
B49: Diferencia Total Mes (Ingreso - Gasto) | C49: =C6-C48
B50: ¿Cuadra el mes? | C50: =IF(C49>=0,"✅ Cuadra","⚠️ Revisar - te faltó dinero")

Sheet Mes 2
B2: MOVIMIENTOS — MES 2
B4: Ingreso Quincena 1 | C4: =ROUND('Gastos Fijos'!C20/2,0)
B5: Ingreso Quincena 2 | C5: ='Gastos Fijos'!C20-C4
B6: INGRESO TOTAL MES | C6: =C4+C5
B8: Fecha | C8: Quincena | D8: Categoría | E8: Acreedor (si es pago tarjeta) | F8: Valor | G8: Tipo | H8: Notas
B43: RESUMEN Y CUADRE
B44: Gastado Quincena 1 | C44: =SUMIFS(F9:F40,C9:C40,"Quincena 1")
B45: Gastado Quincena 2 | C45: =SUMIFS(F9:F40,C9:C40,"Quincena 2")
B46: Saldo Quincena 1 (Ingreso - Gastado) | C46: =C4-C44
B47: Saldo Quincena 2 (Ingreso - Gastado) | C47: =C5-C45
B48: Gasto Total del Mes | C48: =C44+C45
B49: Diferencia Total Mes (Ingreso - Gasto) | C49: =C6-C48
B50: ¿Cuadra el mes? | C50: =IF(C49>=0,"✅ Cuadra","⚠️ Revisar - te faltó dinero")

Sheet Mes 3
B2: MOVIMIENTOS — MES 3
B4: Ingreso Quincena 1 | C4: =ROUND('Gastos Fijos'!C20/2,0)
B5: Ingreso Quincena 2 | C5: ='Gastos Fijos'!C20-C4
B6: INGRESO TOTAL MES | C6: =C4+C5
B8: Fecha | C8: Quincena | D8: Categoría | E8: Acreedor (si es pago tarjeta) | F8: Valor | G8: Tipo | H8: Notas
B43: RESUMEN Y CUADRE
B44: Gastado Quincena 1 | C44: =SUMIFS(F9:F40,C9:C40,"Quincena 1")
B45: Gastado Quincena 2 | C45: =SUMIFS(F9:F40,C9:C40,"Quincena 2")
B46: Saldo Quincena 1 (Ingreso - Gastado) | C46: =C4-C44
B47: Saldo Quincena 2 (Ingreso - Gastado) | C47: =C5-C45
B48: Gasto Total del Mes | C48: =C44+C45
B49: Diferencia Total Mes (Ingreso - Gasto) | C49: =C6-C48
B50: ¿Cuadra el mes? | C50: =IF(C49>=0,"✅ Cuadra","⚠️ Revisar - te faltó dinero")
